datasette_sitemap/__init__.py
datasette_sitemap/hookspecs.py
datasette_sitemap-1.0.dist-info/LICENSE
datasette_sitemap-1.0.dist-info/METADATA
datasette_sitemap-1.0.dist-info/WHEEL
datasette_sitemap-1.0.dist-info/entry_points.txt
datasette_sitemap-1.0.dist-info/top_level.txt
datasette_sitemap-1.0.dist-info/RECORD
