Metadata-Version: 2.1
Name: datasette-sitemap
Version: 1.0
Summary: Generate sitemap.xml for Datasette sites
Home-page: https://github.com/simonw/datasette-sitemap
Author: Simon Willison
License: Apache License, Version 2.0
Project-URL: Issues, https://github.com/simonw/datasette-sitemap/issues
Project-URL: CI, https://github.com/simonw/datasette-sitemap/actions
Project-URL: Changelog, https://github.com/simonw/datasette-sitemap/releases
Classifier: Framework :: Datasette
Classifier: License :: OSI Approved :: Apache Software License
Requires-Python: >=3.7
License-File: LICENSE
Requires-Dist: datasette
Provides-Extra: test
Requires-Dist: pytest ; extra == 'test'
Requires-Dist: pytest-asyncio ; extra == 'test'
Requires-Dist: datasette-block-robots ; extra == 'test'
